deepopt/__init__.py
deepopt/acquisition.py
deepopt/configuration.py
deepopt/deepopt_cli.py
deepopt/defaults.py
deepopt/deltaenc.py
deepopt/models.py
deepopt/nn_ensemble.py
deepopt/surrogate_utils.py
deepopt-0.2.7.dist-info/licenses/LICENSE.md
deepopt-0.2.7.dist-info/licenses/NOTICE.md
deepopt-0.2.7.dist-info/METADATA
deepopt-0.2.7.dist-info/WHEEL
deepopt-0.2.7.dist-info/entry_points.txt
deepopt-0.2.7.dist-info/top_level.txt
deepopt-0.2.7.dist-info/RECORD
