Metadata-Version: 2.4
Name: deepopt
Version: 0.2.7
Summary: Easy-to-use library for Bayesian optimization, with support for neural network surrogates.
Home-page: https://github.com/LLNL/deepopt
Author: DeepOpt Dev Team
Author-email: deepopt@llnl.gov
License: MIT
Classifier: Programming Language :: Python :: 3.8
Classifier: Programming Language :: Python :: 3.9
Requires-Python: >=3.8
License-File: LICENSE.md
License-File: NOTICE.md
Requires-Dist: numpy
Requires-Dist: tqdm
Requires-Dist: scikit-learn
Requires-Dist: torch
Requires-Dist: torchvision
Requires-Dist: gpytorch==1.8.1
Requires-Dist: botorch==0.6.6
Requires-Dist: plotly
Requires-Dist: kaleido
Requires-Dist: ray[tune]
Requires-Dist: scipy
Requires-Dist: click>=8.1.0
Requires-Dist: pyyaml
Requires-Dist: psutil
Requires-Dist: matplotlib
Dynamic: author
Dynamic: author-email
Dynamic: classifier
Dynamic: description
Dynamic: home-page
Dynamic: license
Dynamic: license-file
Dynamic: requires-dist
Dynamic: requires-python
Dynamic: summary
